terrajinja/imports/commvault/__init__.py
terrajinja/imports/commvault/py.typed
terrajinja/imports/commvault/_jsii/__init__.py
terrajinja/imports/commvault/_jsii/commvault@0.0.0.jsii.tgz
terrajinja/imports/commvault/amazon_hypervisor/__init__.py
terrajinja/imports/commvault/aws_storage/__init__.py
terrajinja/imports/commvault/azure_hypervisor/__init__.py
terrajinja/imports/commvault/azure_storage/__init__.py
terrajinja/imports/commvault/company/__init__.py
terrajinja/imports/commvault/credential_aws/__init__.py
terrajinja/imports/commvault/credential_awswithrolearn/__init__.py
terrajinja/imports/commvault/credential_azure/__init__.py
terrajinja/imports/commvault/credential_azurewithtenantid/__init__.py
terrajinja/imports/commvault/data_commvault_client/__init__.py
terrajinja/imports/commvault/data_commvault_clientgroup/__init__.py
terrajinja/imports/commvault/data_commvault_company/__init__.py
terrajinja/imports/commvault/data_commvault_credential/__init__.py
terrajinja/imports/commvault/data_commvault_hyperscale/__init__.py
terrajinja/imports/commvault/data_commvault_kubernetes_applications/__init__.py
terrajinja/imports/commvault/data_commvault_kubernetes_labels/__init__.py
terrajinja/imports/commvault/data_commvault_kubernetes_namespaces/__init__.py
terrajinja/imports/commvault/data_commvault_kubernetes_storageclasses/__init__.py
terrajinja/imports/commvault/data_commvault_kubernetes_volumes/__init__.py
terrajinja/imports/commvault/data_commvault_permission/__init__.py
terrajinja/imports/commvault/data_commvault_plan/__init__.py
terrajinja/imports/commvault/data_commvault_region/__init__.py
terrajinja/imports/commvault/data_commvault_role/__init__.py
terrajinja/imports/commvault/data_commvault_storagepool/__init__.py
terrajinja/imports/commvault/data_commvault_timezone/__init__.py
terrajinja/imports/commvault/data_commvault_user/__init__.py
terrajinja/imports/commvault/data_commvault_usergroup/__init__.py
terrajinja/imports/commvault/disk_accesspath/__init__.py
terrajinja_imports_commvault-1.2.10.dist-info/LICENSE
terrajinja_imports_commvault-1.2.10.dist-info/METADATA
terrajinja_imports_commvault-1.2.10.dist-info/WHEEL
terrajinja_imports_commvault-1.2.10.dist-info/top_level.txt
terrajinja_imports_commvault-1.2.10.dist-info/RECORD
